{
	"name": "df_emp_dept",
	"properties": {
		"type": "MappingDataFlow",
		"typeProperties": {
			"sources": [
				{
					"dataset": {
						"referenceName": "DS_ADLS_SRC_EMP",
						"type": "DatasetReference"
					},
					"name": "source1"
				},
				{
					"dataset": {
						"referenceName": "DS_ADLS_SRC_DEPT",
						"type": "DatasetReference"
					},
					"name": "source2"
				},
				{
					"dataset": {
						"referenceName": "DS_ADLS_SRC_EMP",
						"type": "DatasetReference"
					},
					"name": "source3"
				}
			],
			"sinks": [
				{
					"dataset": {
						"referenceName": "DS_BLOB_TGT_JOIN",
						"type": "DatasetReference"
					},
					"name": "sink1"
				},
				{
					"dataset": {
						"referenceName": "DS_BLOB_TGT_EMP",
						"type": "DatasetReference"
					},
					"name": "sink2"
				},
				{
					"dataset": {
						"referenceName": "DS_BLOB_TGT_EMP",
						"type": "DatasetReference"
					},
					"name": "sink3"
				},
				{
					"dataset": {
						"referenceName": "DS_BLOB_TGT_EMP",
						"type": "DatasetReference"
					},
					"name": "sink4"
				}
			],
			"transformations": [
				{
					"name": "Join1"
				},
				{
					"name": "ConditionalSplit1"
				}
			],
			"script": "source(output(\n\t\tEMPNO as integer,\n\t\tENAME as string,\n\t\tJOB as string,\n\t\tMGR as integer,\n\t\tHIREDATE as date,\n\t\tSAL as integer,\n\t\tCOMM as integer,\n\t\tDEPTNO as integer\n\t),\n\tallowSchemaDrift: true,\n\tvalidateSchema: false,\n\tignoreNoFilesFound: false) ~> source1\nsource(output(\n\t\tDeptno as integer,\n\t\tDname as string,\n\t\tLoc as string\n\t),\n\tallowSchemaDrift: true,\n\tvalidateSchema: false,\n\tignoreNoFilesFound: false) ~> source2\nsource(output(\n\t\tEMPNO as string,\n\t\tENAME as string,\n\t\tJOB as string,\n\t\tMGR as string,\n\t\tHIREDATE as string,\n\t\tSAL as string,\n\t\tCOMM as string,\n\t\tDEPTNO as string\n\t),\n\tallowSchemaDrift: true,\n\tvalidateSchema: false,\n\tignoreNoFilesFound: false) ~> source3\nsource1, source2 join(source1@DEPTNO == source2@Deptno,\n\tjoinType:'inner',\n\tbroadcast: 'auto')~> Join1\nsource3 split(DEPTNO == '10',\n\tDEPTNO == '20',\n\tdisjoint: false) ~> ConditionalSplit1@(dept10, dept20, otherdept)\nJoin1 sink(allowSchemaDrift: true,\n\tvalidateSchema: false,\n\tpartitionFileNames:['emp_dept_inner_join.csv'],\n\tpartitionBy('hash', 1),\n\tskipDuplicateMapInputs: true,\n\tskipDuplicateMapOutputs: true) ~> sink1\nConditionalSplit1@dept10 sink(allowSchemaDrift: true,\n\tvalidateSchema: false,\n\tskipDuplicateMapInputs: true,\n\tskipDuplicateMapOutputs: true) ~> sink2\nConditionalSplit1@dept20 sink(allowSchemaDrift: true,\n\tvalidateSchema: false,\n\tskipDuplicateMapInputs: true,\n\tskipDuplicateMapOutputs: true) ~> sink3\nConditionalSplit1@otherdept sink(allowSchemaDrift: true,\n\tvalidateSchema: false,\n\tskipDuplicateMapInputs: true,\n\tskipDuplicateMapOutputs: true) ~> sink4"
		}
	}
}